MANIFEST.in
README.rst
pyproject.toml
setup.cfg
setup.py
bin/cosmos
bin/run_pyfunc
cosmos/VERSION
cosmos/__init__.py
cosmos/api.py
cosmos/constants.py
cosmos/db.py
cosmos/core/__init__.py
cosmos/core/cmd_fxn/__init__.py
cosmos/core/cmd_fxn/signature.py
cosmos/graph/__init__.py
cosmos/graph/draw.py
cosmos/job/JobManager.py
cosmos/job/__init__.py
cosmos/job/drm/DRM_Base.py
cosmos/job/drm/__init__.py
cosmos/job/drm/drm_awsbatch.py
cosmos/job/drm/drm_drmaa.py
cosmos/job/drm/drm_ge.py
cosmos/job/drm/drm_k8s_jobs.py
cosmos/job/drm/drm_local.py
cosmos/job/drm/drm_lsf.py
cosmos/job/drm/drm_slurm.py
cosmos/job/drm/util.py
cosmos/models/Cosmos.py
cosmos/models/Stage.py
cosmos/models/Task.py
cosmos/models/Workflow.py
cosmos/models/__init__.py
cosmos/test/__init__.py
cosmos/test/test_edge_cases.py
cosmos/test/test_examples.py
cosmos/test/test_gpus_local_drm.py
cosmos/test/misc/__init__.py
cosmos/test/misc/massive_workflow.py
cosmos/util/__init__.py
cosmos/util/args.py
cosmos/util/growl.py
cosmos/util/helpers.py
cosmos/util/iterstuff.py
cosmos/util/retry.py
cosmos/util/signal_handlers.py
cosmos/util/sms.py
cosmos/util/sqla.py
cosmos/util/task_helpers.py
cosmos/web/__init__.py
cosmos/web/filters.py
cosmos/web/gunicorn.py
cosmos/web/views.py
cosmos/web/gemon/__init__.py
cosmos/web/gemon/ge.py
cosmos/web/gemon/util.py
cosmos/web/gemon/views.py
cosmos/web/static/custom.css
cosmos/web/static/jquery.dataTables.min.js
cosmos/web/static/bootstrap3/css/bootstrap-theme.css
cosmos/web/static/bootstrap3/css/bootstrap-theme.min.css
cosmos/web/static/bootstrap3/css/bootstrap.css
cosmos/web/static/bootstrap3/css/bootstrap.min.css
cosmos/web/static/bootstrap3/fonts/glyphicons-halflings-regular.eot
cosmos/web/static/bootstrap3/fonts/glyphicons-halflings-regular.svg
cosmos/web/static/bootstrap3/fonts/glyphicons-halflings-regular.ttf
cosmos/web/static/bootstrap3/fonts/glyphicons-halflings-regular.woff
cosmos/web/static/bootstrap3/js/bootstrap.js
cosmos/web/static/bootstrap3/js/bootstrap.min.js
cosmos_wfm.egg-info/PKG-INFO
cosmos_wfm.egg-info/SOURCES.txt
cosmos_wfm.egg-info/dependency_links.txt
cosmos_wfm.egg-info/requires.txt
cosmos_wfm.egg-info/top_level.txt
