Metadata-Version: 2.1
Name: cosmos-wfm
Version: 2.13.11
Summary: Workflow Management System
Home-page: https://mizzou-cbmi.github.io/
Author: Erik Gafni
Author-email: egafni@gmail.com
Maintainer: Erik Gafni
Maintainer-email: egafni@gmail.com
License: GPL v3
Keywords: workflow machine learning ipeline ngs manager management distributed sge slurm genomics sequencing grid computing scientific
Platform: UNKNOWN
Classifier: Programming Language :: Python :: 3.6
Classifier: Programming Language :: Python :: 3.7
Classifier: Programming Language :: Python :: 3.8
Classifier: Intended Audience :: Developers
Classifier: License :: OSI Approved :: GNU General Public License v3 (GPLv3)
Classifier: Operating System :: MacOS
Classifier: Operating System :: Microsoft :: Windows
Classifier: Operating System :: POSIX
Classifier: Programming Language :: Python
Classifier: Topic :: Software Development
Classifier: Topic :: Utilities
Provides-Extra: test
